notebookr/__init__.py
notebookr/cli.py
notebookr-0.1.5.dist-info/METADATA
notebookr-0.1.5.dist-info/WHEEL
notebookr-0.1.5.dist-info/entry_points.txt
notebookr-0.1.5.dist-info/RECORD
