Metadata-Version: 2.4
Name: notebookr
Version: 0.1.5
Summary: Setup development environment for Jupyter notebooks using UV
Project-URL: Homepage, https://github.com/peterdresslar/notebookr
Project-URL: Bug Tracker, https://github.com/peterdresslar/notebookr/issues
Author-email: Peter Dresslar <peterdresslar@gmail.com>
Keywords: academic,development,jupyter,notebook,python,research,uv,virtualenv
Classifier: Operating System :: OS Independent
Classifier: Programming Language :: Python :: 3
Requires-Python: >=3.7
Requires-Dist: stdlib-list>=0.10.0
